{"Teacher": 0, "Worker": 1, "Farmer": 2, "Scientist": 3, "Doctor": 4, "Police": 5, "Firemen": 6, "Merchant": 7, "Infant": 8, "Boy": 9, "Girl": 10, "MaleYoungsters": 11, "FemaleYoungsters": 12, "Father": 13, "Mother": 14, "GreatGrandfather": 15, "GreatGrandmother": 16, "FearPerson": 17, "HappyPerson": 18, "CryPerson": 19, "AngryPerson": 20, "Backpackers": 21, "OldFisherman": 22, "ReadingPerson": 23, "ACoupleInWedding": 24, "DancingPerson": 25, "PlayingPerson": 26, "Squatter": 27, "SittingPerson": 28, "LyingPerson": 29, "StandPerson": 30, "KneelsPerson": 31, "Jesus": 32, "OrdBuddha": 33, "Avalokitesvara": 34, "Nabi": 35, "VirginMary": 36, "IndiaShiva": 37, "LionHead": 38, "Angel": 39, "Nun": 40, "Pastor": 41, "Muslim_female": 42, "Monk": 43, "Adam": 44, "Eve": 45, "TangSMonk": 46, "MonkeyKing": 47, "PigEightQuit": 48, "SandMonk": 49, "WhiteDragonHorse": 50, "Mermaid": 51, "Centaur": 52, "Tauren": 53, "Athena": 54, "Dwarf": 55, "Extra_terrestrial": 56, "Pinocchio": 57, "King": 58, "Prince": 59, "Princess": 60, "Knight": 61, "Superman": 62, "Enchanter": 63, "Santa": 64, "SonGoku": 65, "Doraemon": 66, "Altman": 67, "Conan": 68, "Brokeback": 69, "BrokeLeg": 70, "Eyes": 71, "Ear": 72, "Nose": 73, "Lips": 74, "Breast": 75, "Penis": 76, "SkeletonMan": 77, "HumanSkull": 78, "Vampire": 79, "WhiteLady": 80, "Zombies": 81, "Witch": 82, "Rat": 83, "Cow": 84, "Tiger": 85, "Rabbit": 86, "Snake": 87, "Horse": 88, "Sheep": 89, "Monkey": 90, "Dog": 91, "Pig": 92, "Elephant": 93, "Crocodile": 94, "Tortoise": 95, "Lion": 96, "Cat": 97, "Panda": 98, "Chicken": 99, "Duck": 100, "Peacock": 101, "MandarinDuck": 102, "Eagle": 103, "Penguin": 104, "Owl": 105, "Bat": 106, "Parrot": 107, "Feather": 108, "Caterpillar": 109, "Butterfly": 110, "Spider": 111, "Mantis": 112, "TheAnts": 113, "Centipede": 114, "Scorpion": 115, "LadyBeetle": 116, "Fly": 117, "WormCocoon": 118, "SpiderWeb": 119, "Shark": 120, "BaleenWhales": 121, "Octopus": 122, "Carp": 123, "DevilRays": 124, "Goldfish": 125, "Dolphins": 126, "Crab": 127, "Shrimp": 128, "Snail": 129, "Frog": 130, "Starfish": 131, "Dragon": 132, "Phoenix": 133, "Hellhound": 134, "FlyingHorse": 135, "unicorn": 136, "TyrannosaurusRex": 137, "Mammoths": 138, "Archaeopteryx": 139, "Stegosaurus": 140, "Diplodocus": 141, "CoconutTree": 142, "DeadTree": 143, "PineTree": 144, "ChristmasTree": 145, "Bamboo": 146, "TheWillowTree": 147, "RedMaple": 148, "BigBanyanTree": 149, "SingleLeaf": 150, "SingleRose": 151, "Peonies": 152, "Chrysanthem": 153, "Lotus": 154, "Bouquet": 155, "Grass": 156, "Cactus": 157, "Seaweed": 158, "Cabbage": 159, "Corn": 160, "Peanut": 161, "Carrots": 162, "Chili": 163, "Mushroom": 164, "Pumpkin": 165, "Tomatoes": 166, "Watermelon": 167, "Grapes": 168, "Apple": 169, "Banana": 170, "Orange": 171, "Strawberry": 172, "Durian": 173, "Pineapple": 174, "Hospital": 175, "School": 176, "Bank": 177, "PoliceStation": 178, "ResidentialBuilding": 179, "TheAmusementPark": 180, "GasStation": 181, "ShoppingCenter": 182, "Hotel": 183, "Stadium": 184, "SingleVillas": 185, "Farmyard": 186, "Pavilion": 187, "WaterWheel": 188, "AHut": 189, "WoodenBridge": 190, "Arch": 191, "Windmill": 192, "Grave": 193, "Swing": 194, "Lighthouse": 195, "Wells": 196, "ATelephoneBooth": 197, "TheBusStop": 198, "ModernBridge": 199, "APublicToilet": 200, "TheFerrisWheel": 201, "EiffelTower": 202, "TheCastleInGermany": 203, "TheGreatWall": 204, "Pyramid": 205, "TheStatueOfLiberty": 206, "PisaTower": 207, "Colosseum": 208, "Parthenon": 209, "Door": 210, "Fence": 211, "FenceWall": 212, "BarbedWire": 213, "ChineseTemples": 214, "CatholicChurch": 215, "Pagoda": 216, "ChristTheRedeemer": 217, "TheTajMahal": 218, "Obelisk": 219, "IndianTotemPole": 220, "Bed": 221, "Table": 222, "Chair": 223, "Sofa": 224, "TeaTable": 225, "Wardrobe": 226, "Dresser": 227, "Ambry": 228, "Screen": 229, "VerticalBell": 230, "Desk": 231, "TV": 232, "Computer": 233, "Refrigerator": 234, "MobilePhone": 235, "FloorLamp": 236, "Commode": 237, "Bathtub": 238, "FlushToilet": 239, "RiceBowl": 240, "Dishes": 241, "Knife": 242, "Fork": 243, "Spoon": 244, "Teapot": 245, "TeaCup": 246, "WineBottle": 247, "RedWineGlass": 248, "Candlestick": 249, "GoldIngot": 250, "TheAncientCopper": 251, "TreasureChest": 252, "JadeRuyi": 253, "Basketball": 254, "Football": 255, "Piano": 256, "Guitar": 257, "Go": 258, "BraisedPork": 259, "ACartonOfSushi": 260, "SauteedVegetables": 261, "OneHallOfCoke": 262, "ABowlOfRice": 263, "AHamburger": 264, "APlateOfSweets": 265, "APizza": 266, "Car": 267, "Train": 268, "Bicycle": 269, "Carriage": 270, "Excavator": 271, "Bulldozer": 272, "Truck": 273, "PoliceCar": 274, "Ambulance": 275, "Fire": 276, "WindSailing": 277, "BigCruise": 278, "Raft": 279, "PrivateLuxuryYacht": 280, "PassengerPlane": 281, "Helicopter": 282, "FlyingSaucer": 283, "HotAirBalloon": 284, "Airship": 285, "PropellerPlane": 286, "Road": 287, "Tracks": 288, "StreetLamp": 289, "NoRoadSigns": 290, "ParkingSign": 291, "Bonfire": 292, "SpringWater": 293, "Rainbow": 294, "GlassBall": 295, "CrystalClumpOfMine": 296, "CoralTree": 297, "Scallops": 298, "StoneMountain": 299, "SnowMountain": 300, "Thevolcano": 301, "ChristianCross": 302, "IslamicCrescent": 303, "TheEyeOfHorusSign": 304, "TaiChiSymbol": 305, "ThousandsOfCharacters": 306, "PentacleSymbol": 307, "BuddhistWheelSymbol": 308, "OuroborosSymbol": 309, "FairSymbol": 310, "Anti-warSymbol": 311, "WheelOfDestinysymbol": 312, "StarOfDavidSymbol": 313, "OmSymbols": 314, "Tanks": 315, "Cannon": 316, "AircraftCarrier": 317, "Fighter": 318, "ArmoredVehicles": 319, "Warship": 320, "CampTents": 321, "Bunker": 322, "Flagblue": 323, "Flagred": 324, "Flagyellow": 325, "Fortifications": 326, "ASoldierInFiringCondition": 327, "ASoldierStandingAtAttention": 328, "CrawlingSoldiers": 329, "ASoldierCrouchingAndAiming": 330, "NativesWithSpears": 331, "AboriginesWithBowsAndArrows": 332, "AboriginesWithMachetes": 333, "Magician1": 334, "Magician2": 335, "Policemen1": 336, "Germancharacters": 337, "LittleMonk1": 338, "GreatGrandfather1": 339, "Infant1": 340, "Boy3": 341, "Boy4": 342, "Boy5": 343, "Woman1": 344, "HappyPerson1": 345, "StandPerson1": 346, "StandPerson2": 347, "SittingPerson1": 348, "Avalokitesvara1": 349, "CaptainAmerica": 350, "RobotWarrior": 351, "ArmorWarrior": 352, "Santa1": 353, "Zombie1": 354, "CartoonZombie": 355, "Witch1": 356, "Witch2": 357, "SculptureSkull": 358, "PlaygroundSlide": 359, "GasStation1": 360, "FuelDispenser": 361, "Building1": 362, "Building2": 363, "Building3": 364, "House3": 365, "House4": 366, "CartoonBuilding": 367, "EuropeanArchitecture": 368, "Mansion1": 369, "villa1": 370, "villa2": 371, "villa3": 372, "House1": 373, "House2": 374, "House5": 375, "WoodenHouse1": 376, "WoodenHouse2": 377, "Pavilion1": 378, "Pavilion2": 379, "WoodenArchBridge": 380, "StoneBridge": 381, "Mailbox": 382, "StreetLamp1": 383, "ATM1": 384, "Fence1": 385, "Church2": 386, "Church3": 387, "SUV1": 388, "Car1": 389, "JEEP ": 390, "RV": 391, "Van1": 392, "Locomotive": 393, "Taxi": 394, "SmallWoodenBoat": 395, "Boat1": 396, "Boat2": 397, "Boat3": 398, "Steamship1": 399, "TransportShip": 400, "Sailboat1": 401, "SmallFishingBoat": 402, "Cruiseship1": 403, "Cruiseship2": 404, "Aircraft1": 405, "Aircraft2": 406, "Helicopter1": 407, "Helicopter2": 408, "Helicopter3": 409, "FanTree": 410, "FallenTree": 411, "Trunk": 412, "Sunflower": 413, "WhiteRose": 414, "Daffodil": 415, "Lily": 416, "Flowerbed": 417, "RedRose": 418, "winterJasmine": 419, "Anthurium": 420, "Phalaenopsis1": 421, "FlowerBush": 422, "Cactus1": 423, "WealthyBamboo": 424, "Weeds": 425, "Cherry": 426, "FruitBasket": 427, "Stone1": 428, "Stone2": 429, "Chair1": 430, "WoodenChair": 431, "DoubleSofa": 432, "BabyBed": 433, "RoundTable": 434, "Mirror": 435, "TableLamp1": 436, "TableLamp2": 437, "LightBulb": 438, "EmergencyLight": 439, "PetrolLamp": 440, "Searchlight": 441, "Candle": 442, "Glass": 443, "Cup": 444, "DrumKit": 445, "ElectronicOrgan": 446, "Phone": 447, "Radio": 448, "AlarmClock": 449, "PotatoChips": 450, "Cake": 451, "Bread": 452, "Liqueur": 453, "Ginger": 454, "ChickenLeg": 455, "Rice": 456, "Meat": 457, "Ham": 458, "CannedCookedFood": 459, "Coffee": 460, "StrawberryJam": 461, "Beer": 462, "Lemon": 463, "BasketOfPears": 464, "Donuts": 465, "Yogurt": 466, "Potato": 467, "RoastChicken": 468, "Coke": 469, "ChewingGum": 470, "Egg": 471, "Biscuit": 472, "Chocolate": 473, "Litchi": 474, "Skewers": 475, "Snake1": 476, "Leopard": 477, "BrownBear": 478, "Wolf": 479, "Tortoise1": 480, "Tortoise2": 481, "Tortoise3": 482, "Cat1": 483, "Puppy": 484, "Dog1": 485, "Chicken1": 486, "Shark1": 487, "Fish1": 488, "Fish2": 489, "Snail1": 490, "Dog2": 491, "lawn": 492, "grass1": 493}